clue/.gitignore
clue/__init__.py
clue/api/__init__.py
clue/api/base.py
clue/api/v1/__init__.py
clue/api/v1/actions.py
clue/api/v1/auth.py
clue/api/v1/configs.py
clue/api/v1/fetchers.py
clue/api/v1/lookup.py
clue/api/v1/registration.py
clue/api/v1/static.py
clue/app.py
clue/cache/__init__.py
clue/common/__init__.py
clue/common/classification.py
clue/common/classification.yml
clue/common/dict_utils.py
clue/common/exceptions.py
clue/common/forge.py
clue/common/json_utils.py
clue/common/list_utils.py
clue/common/logging/__init__.py
clue/common/logging/audit.py
clue/common/logging/format.py
clue/common/regex.py
clue/common/str_utils.py
clue/common/swagger.py
clue/common/uid.py
clue/config.py
clue/constants/__init__.py
clue/constants/supported_types.py
clue/cronjobs/__init__.py
clue/cronjobs/plugins.py
clue/error.py
clue/extensions/__init__.py
clue/extensions/config.py
clue/gunicorn_config.py
clue/healthz.py
clue/helper/discover.py
clue/helper/headers.py
clue/helper/oauth.py
clue/models/__init__.py
clue/models/actions.py
clue/models/config.py
clue/models/fetchers.py
clue/models/graph.py
clue/models/model_list.py
clue/models/network.py
clue/models/results/__init__.py
clue/models/results/base.py
clue/models/results/graph.py
clue/models/results/image.py
clue/models/results/status.py
clue/models/results/validation.py
clue/models/selector.py
clue/models/validators.py
clue/patched.py
clue/plugin/__init__.py
clue/plugin/helpers/__init__.py
clue/plugin/helpers/central_server.py
clue/plugin/helpers/email_render.py
clue/plugin/helpers/token.py
clue/plugin/helpers/trino.py
clue/plugin/models.py
clue/plugin/utils.py
clue/py.typed
clue/remote/__init__.py
clue/remote/datatypes/__init__.py
clue/remote/datatypes/cache.py
clue/remote/datatypes/events.py
clue/remote/datatypes/hash.py
clue/remote/datatypes/queues/__init__.py
clue/remote/datatypes/queues/comms.py
clue/remote/datatypes/set.py
clue/remote/datatypes/user_quota_tracker.py
clue/security/__init__.py
clue/security/obo.py
clue_api-1.2.1.46.dist-info/METADATA
clue_api-1.2.1.46.dist-info/WHEEL
clue_api-1.2.1.46.dist-info/entry_points.txt
clue_api-1.2.1.46.dist-info/licenses/LICENSE
clue_api-1.2.1.46.dist-info/RECORD
