Metadata-Version: 2.4
Name: clue-api
Version: 1.2.1.46
Summary: Clue distributed enrichment service
License: MIT
License-File: LICENSE
Keywords: clue,distributed,enrichment,gc,canada,cse-cst,cse,cst,cyber,cccs
Author: Canadian Centre for Cyber Security
Author-email: contact@cyber.gc.ca
Requires-Python: >=3.12,<4.0
Classifier: Development Status :: 5 - Production/Stable
Classifier: Intended Audience :: Developers
Classifier: License :: OSI Approved :: MIT License
Classifier: Programming Language :: Python :: 3
Classifier: Programming Language :: Python :: 3.12
Classifier: Programming Language :: Python :: 3.13
Classifier: Programming Language :: Python :: 3.14
Classifier: Topic :: Software Development :: Libraries
Provides-Extra: server
Requires-Dist: PyYAML (>=6.0.1,<7.0.0) ; extra == "server"
Requires-Dist: Werkzeug (>=3.0.2,<4.0.0) ; extra == "server"
Requires-Dist: apscheduler (>=3.10.4,<4.0.0) ; extra == "server"
Requires-Dist: authlib (<2.0.0) ; extra == "server"
Requires-Dist: bcrypt (>=4.1.2,<5.0.0) ; extra == "server"
Requires-Dist: beautifulsoup4 (>=4.13.3,<5.0.0)
Requires-Dist: cart (>=1.2.3,<2.0.0)
Requires-Dist: elastic-apm (>=6.22.0,<7.0.0)
Requires-Dist: flasgger (>=0.9.7.1,<0.10.0.0) ; extra == "server"
Requires-Dist: flask (<3.0.0)
Requires-Dist: flask-caching (>=2.1.0,<3.0.0)
Requires-Dist: flask-cors (>=4.0.1,<7.0.0) ; extra == "server"
Requires-Dist: gevent (>=24.2.1,<25.0.0)
Requires-Dist: geventhttpclient (>=2.3.1,<3.0.0)
Requires-Dist: gunicorn (>=22,<24)
Requires-Dist: imgkit (>=1.2.3,<2.0.0)
Requires-Dist: passlib (>=1.7.4,<2.0.0) ; extra == "server"
Requires-Dist: pillow (>=11.1.0,<12.0.0)
Requires-Dist: prometheus-client (>=0.20.0,<0.21.0) ; extra == "server"
Requires-Dist: pydantic (>=2.7.1,<3.0.0)
Requires-Dist: pydantic-settings[yaml] (>=2.3.4,<3.0.0)
Requires-Dist: pyjwt (>=2.8.0,<3.0.0) ; extra == "server"
Requires-Dist: pyroute2 (>=0.7.12,<0.8.0) ; extra == "server"
Requires-Dist: python-baseconv (>=1.2.2,<2.0.0) ; extra == "server"
Requires-Dist: pytz (>=2024.1,<2025.0) ; extra == "server"
Requires-Dist: redis (>=5.0.3,<6.0.0)
Requires-Dist: requests (>=2.32.5,<3.0.0)
Requires-Dist: setuptools (<79.0.0)
Requires-Dist: trino (>=0.336.0,<0.337.0)
Project-URL: Documentation, https://github.com/CybercentreCanada/clue
Project-URL: Homepage, https://github.com/CybercentreCanada/clue
Project-URL: Repository, https://github.com/CybercentreCanada/clue
